openwisp_utils/__init__.py
openwisp_utils/admin.py
openwisp_utils/base.py
openwisp_utils/cliff.toml
openwisp_utils/fields.py
openwisp_utils/loaders.py
openwisp_utils/qa.py
openwisp_utils/settings.py
openwisp_utils/staticfiles.py
openwisp_utils/storage.py
openwisp_utils/tasks.py
openwisp_utils/test_selenium_mixins.py
openwisp_utils/utils.py
openwisp_utils/validators.py
openwisp_utils/admin_theme/__init__.py
openwisp_utils/admin_theme/admin.py
openwisp_utils/admin_theme/apps.py
openwisp_utils/admin_theme/checks.py
openwisp_utils/admin_theme/context_processor.py
openwisp_utils/admin_theme/dashboard.py
openwisp_utils/admin_theme/email.py
openwisp_utils/admin_theme/filters.py
openwisp_utils/admin_theme/menu.py
openwisp_utils/admin_theme/settings.py
openwisp_utils/admin_theme/system_info.py
openwisp_utils/admin_theme/theme.py
openwisp_utils/admin_theme/views.py
openwisp_utils/admin_theme/static/admin/css/help-text-stacked.css
openwisp_utils/admin_theme/static/admin/css/openwisp-info.css
openwisp_utils/admin_theme/static/admin/css/openwisp.css
openwisp_utils/admin_theme/static/admin/css/ow-auto-filter.css
openwisp_utils/admin_theme/static/admin/css/ow-dashboard.css
openwisp_utils/admin_theme/static/admin/css/ow-filters.css
openwisp_utils/admin_theme/static/admin/fonts/LICENSE.txt
openwisp_utils/admin_theme/static/admin/fonts/README.txt
openwisp_utils/admin_theme/static/admin/fonts/Roboto-Bold-webfont.woff
openwisp_utils/admin_theme/static/admin/fonts/Roboto-Light-webfont.woff
openwisp_utils/admin_theme/static/admin/fonts/Roboto-Regular-webfont.woff
openwisp_utils/admin_theme/static/admin/js/menu.js
openwisp_utils/admin_theme/static/admin/js/ow-auto-filter.js
openwisp_utils/admin_theme/static/admin/js/ow-dashboard.js
openwisp_utils/admin_theme/static/admin/js/ow-filter.js
openwisp_utils/admin_theme/static/admin/vendor/js/plotly-cartesian.min.js
openwisp_utils/admin_theme/static/drf-yasg/ow-drf-yasg.css
openwisp_utils/admin_theme/static/rest_framework/css/browsable-api.css
openwisp_utils-1.2.1.dist-info/licenses/LICENSE
openwisp_utils-1.2.1.dist-info/METADATA
openwisp_utils-1.2.1.dist-info/WHEEL
openwisp_utils-1.2.1.dist-info/entry_points.txt
openwisp_utils-1.2.1.dist-info/top_level.txt
openwisp_utils-1.2.1.dist-info/RECORD
